makedeb.sh
mtrax.desktop
mtrax.mime
mtraxicon.ico
setup.py
Mtrax.egg-info/PKG-INFO
Mtrax.egg-info/SOURCES.txt
Mtrax.egg-info/dependency_links.txt
Mtrax.egg-info/eager_resources.txt
Mtrax.egg-info/entry_points.txt
Mtrax.egg-info/native_libs.txt
Mtrax.egg-info/stdeb.cfg
Mtrax.egg-info/top_level.txt
groundtruth/calibrationmovies.csl
groundtruth/choose_orientations.m
groundtruth/compressall_wholeview.pl
groundtruth/cvpred.m
groundtruth/detect_features.m
groundtruth/expmovies.csl
groundtruth/find_lowres2highres_transform.m
groundtruth/fmfreadframe.m
groundtruth/gross_errors.mat
groundtruth/grosserror_notes.txt
groundtruth/grosserrors_annotation_movie20071007_152940.mat
groundtruth/grosserrors_annotation_movie20071007_153946.mat
groundtruth/grosserrors_annotation_movie20071007_162740.mat
groundtruth/identify_close_flies.m
groundtruth/identify_gross_errors.fig
groundtruth/identify_gross_errors.m
groundtruth/identify_gross_errors_20071024T190707.mat
groundtruth/identify_gross_errors_regions.m
groundtruth/identify_possible_errors.m
groundtruth/identify_possible_errors_regions.m
groundtruth/identify_possible_swaps.m
groundtruth/identify_swap_flies.m
groundtruth/labelflies.m
groundtruth/labelflygui.fig
groundtruth/labelflygui.m
groundtruth/labelhighres.m
groundtruth/labelhighrespoints.m
groundtruth/match_features.m
groundtruth/normalize_area.m
groundtruth/normalize_area_zoom_spatial.m
groundtruth/normalizeareaplot.m
groundtruth/readframe.m
groundtruth/runmtrax.pl
groundtruth/sbfmfreadframe.m
groundtruth/showerrors.m
groundtruth/showframe.m
groundtruth/test_choose_orientations.m
groundtruth/wholeviewmovies.csl
groundtruth/zoomed_spatial_test.m
groundtruth/zoomedviewmovies.csl
groundtruth/zoominonflies.m
groundtruth/zoomsizes.m
houghcircles/houghcircles_C.c
hungarian/LICENSE
hungarian/README
hungarian/asp.cpp
hungarian/asp.h
hungarian/changes.txt
hungarian/hungarian.cpp
matlab/angledist2.m
matlab/backsub.m
matlab/compare_filedates.m
matlab/conncomp_track.m
matlab/conncomp_track_frame.m
matlab/cvpred.m
matlab/deleteshorttracks.m
matlab/drawresults.m
matlab/estback.m
matlab/estconncomps.m
matlab/estsize.m
matlab/estsize0.m
matlab/fixlarge.m
matlab/fixorientation.m
matlab/fixsmall.m
matlab/get_identities.m
