Metadata-Version: 1.0
Name: Mtrax
Version: 2.2.07
Summary: Multiple fly tracker
Home-page: http://www.dickinson.caltech.edu/Research/Mtrax
Author: Caltech ethomics project
Author-email: branson@caltech.edu
License: UNKNOWN
Platform: UNKNOWN
